remote_log_analysis/__init__.py
remote_log_analysis/remote_executor_interface.py
remote_log_analysis/remote_file_base.py
remote_log_analysis/remote_linux_executor.py
remote_log_analysis/remote_log_search.py
remote_log_analysis/remote_log_utils.py
remote_log_analysis/remote_path_info.py
remote_log_analysis/remote_text_log.py
remote_log_analysis-0.1.2.dist-info/LICENSE
remote_log_analysis-0.1.2.dist-info/METADATA
remote_log_analysis-0.1.2.dist-info/WHEEL
remote_log_analysis-0.1.2.dist-info/RECORD
