Metadata-Version: 2.1
Name: remote-log-analysis
Version: 0.1.2
Summary: Analyze log files on remote hosts locally
Home-page: https://github.com/kubiyak/remote_log_analysis
License: MIT
Author: Kuberan Naganathan
Author-email: python_cpp_developer@protonmail.com
Requires-Python: >=3.11,<4.0
Classifier: License :: OSI Approved :: MIT License
Classifier: Programming Language :: Python :: 3
Classifier: Programming Language :: Python :: 3.11
Requires-Dist: fabric (>=3.1.0,<4.0.0)
Requires-Dist: pytest (>=7.4.0,<8.0.0)
Requires-Dist: pytest-cov (>=4.1.0,<5.0.0)
Requires-Dist: python-dateutil (>=2.8.2,<3.0.0)
Project-URL: Repository, https://github.com/kubiyak/remote_log_analysis
